README
setup.py
learningml/__init__.py
learningml/text.py
learningml.egg-info/PKG-INFO
learningml.egg-info/SOURCES.txt
learningml.egg-info/dependency_links.txt
learningml.egg-info/not-zip-safe
learningml.egg-info/requires.txt
learningml.egg-info/top_level.txt