Metadata-Version: 1.0
Name: learningml
Version: 0.2
Summary: This repository demonstrates how to make a project pip installable, write a Python module in C++ and use scikit-learn, keras and spearmint.
Home-page: https://github.com/weissercn/learningml
Author: Constantin Weisser
Author-email: weissercn@gmail.com
License: MIT
Platform: UNKNOWN
